[
  {
    "id": "arm9.0000",
    "pos": 360588,
    "length": 7
  },
  {
    "id": "arm9.0001",
    "pos": 360596,
    "length": 7
  },
  {
    "id": "arm9.0002",
    "pos": 360604,
    "length": 7
  },
  {
    "id": "arm9.0003",
    "pos": 360612,
    "length": 7
  },
  {
    "id": "arm9.0004",
    "pos": 360620,
    "length": 7
  },
  {
    "id": "arm9.0005",
    "pos": 360628,
    "length": 7
  },
  {
    "id": "arm9.0006",
    "pos": 360636,
    "length": 7
  },
  {
    "id": "arm9.0007",
    "pos": 360644,
    "length": 7
  },
  {
    "id": "arm9.0008",
    "pos": 360652,
    "length": 7
  },
  {
    "id": "arm9.0009",
    "pos": 360660,
    "length": 7
  },
  {
    "id": "arm9.0010",
    "pos": 360668,
    "length": 7
  },
  {
    "id": "arm9.0011",
    "pos": 360676,
    "length": 7
  },
  {
    "id": "arm9.0012",
    "pos": 360684,
    "length": 7
  },
  {
    "id": "arm9.0013",
    "pos": 360692,
    "length": 7
  },
  {
    "id": "arm9.0014",
    "pos": 360700,
    "length": 7
  },
  {
    "id": "arm9.0015",
    "pos": 360708,
    "length": 7
  },
  {
    "id": "arm9.0016",
    "pos": 360716,
    "length": 7
  },
  {
    "id": "arm9.0017",
    "pos": 360724,
    "length": 7
  },
  {
    "id": "arm9.0018",
    "pos": 360732,
    "length": 7
  },
  {
    "id": "arm9.0019",
    "pos": 360740,
    "length": 7
  },
  {
    "id": "arm9.0020",
    "pos": 360748,
    "length": 11
  },
  {
    "id": "arm9.0021",
    "pos": 360760,
    "length": 11
  },
  {
    "id": "arm9.0022",
    "pos": 360772,
    "length": 11
  },
  {
    "id": "arm9.0023",
    "pos": 360784,
    "length": 11
  },
  {
    "id": "arm9.0024",
    "pos": 360796,
    "length": 11
  },
  {
    "id": "arm9.0025",
    "pos": 360808,
    "length": 11
  },
  {
    "id": "arm9.0026",
    "pos": 360820,
    "length": 13
  },
  {
    "id": "arm9.0027",
    "pos": 360844,
    "length": 15
  },
  {
    "id": "arm9.0028",
    "pos": 360860,
    "length": 15
  },
  {
    "id": "arm9.0029",
    "pos": 360876,
    "length": 15
  },
  {
    "id": "arm9.0030",
    "pos": 360892,
    "length": 15
  },
  {
    "id": "arm9.0031",
    "pos": 360908,
    "length": 15
  },
  {
    "id": "arm9.0032",
    "pos": 360940,
    "length": 15
  },
  {
    "id": "arm9.0033",
    "pos": 360956,
    "length": 19
  },
  {
    "id": "arm9.0034",
    "pos": 360976,
    "length": 19
  },
  {
    "id": "arm9.0035",
    "pos": 360996,
    "length": 19
  },
  {
    "id": "arm9.0036",
    "pos": 361016,
    "length": 23
  },
  {
    "id": "arm9.0037",
    "pos": 361776,
    "length": 35,
    "parts": [
      {
        "id": "arm9.0037.00"
      },
      {
        "text": "%e"
      }
    ]
  },
  {
    "id": "arm9.0038",
    "pos": 361812,
    "length": 35,
    "parts": [
      {
        "id": "arm9.0038.00"
      },
      {
        "text": "%e"
      }
    ]
  },
  {
    "id": "arm9.0039",
    "pos": 361848,
    "length": 39,
    "parts": [
      {
        "id": "arm9.0039.00"
      },
      {
        "text": "%e"
      }
    ]
  },
  {
    "id": "arm9.0040",
    "pos": 361888,
    "length": 43,
    "parts": [
      {
        "id": "arm9.0040.00"
      },
      {
        "text": "%e"
      }
    ]
  },
  {
    "id": "arm9.0041",
    "pos": 361932,
    "length": 51,
    "parts": [
      {
        "id": "arm9.0041.00"
      },
      {
        "text": "%e"
      }
    ]
  },
  {
    "id": "arm9.0042",
    "pos": 361984,
    "length": 51,
    "parts": [
      {
        "id": "arm9.0042.00"
      },
      {
        "text": "%e"
      }
    ]
  },
  {
    "id": "arm9.0043",
    "pos": 362036,
    "length": 55,
    "parts": [
      {
        "id": "arm9.0043.00"
      },
      {
        "text": "%e"
      }
    ]
  },
  {
    "id": "arm9.0044",
    "pos": 362092,
    "length": 55,
    "parts": [
      {
        "id": "arm9.0044.00"
      },
      {
        "text": "%e"
      }
    ]
  },
  {
    "id": "arm9.0045",
    "pos": 362148,
    "length": 59,
    "parts": [
      {
        "id": "arm9.0045.00"
      },
      {
        "text": "%e"
      }
    ]
  },
  {
    "id": "arm9.0046",
    "pos": 362208,
    "length": 59,
    "parts": [
      {
        "id": "arm9.0046.00"
      },
      {
        "text": "%e"
      }
    ]
  },
  {
    "id": "arm9.0047",
    "pos": 362268,
    "length": 59,
    "parts": [
      {
        "id": "arm9.0047.00"
      },
      {
        "text": "%e"
      }
    ]
  },
  {
    "id": "arm9.0048",
    "pos": 362328,
    "length": 63,
    "parts": [
      {
        "id": "arm9.0048.00"
      },
      {
        "text": "%e"
      }
    ]
  },
  {
    "id": "arm9.0049",
    "pos": 362392,
    "length": 67,
    "parts": [
      {
        "id": "arm9.0049.00"
      },
      {
        "text": "%e"
      }
    ]
  },
  {
    "id": "arm9.0050",
    "pos": 362460,
    "length": 67,
    "parts": [
      {
        "id": "arm9.0050.00"
      },
      {
        "text": "%e"
      }
    ]
  },
  {
    "id": "arm9.0051",
    "pos": 362528,
    "length": 67,
    "parts": [
      {
        "id": "arm9.0051.00"
      },
      {
        "text": "%e"
      }
    ]
  },
  {
    "id": "arm9.0052",
    "pos": 362596,
    "length": 67,
    "parts": [
      {
        "id": "arm9.0052.00"
      },
      {
        "text": "%e"
      }
    ]
  },
  {
    "id": "arm9.0053",
    "pos": 362664,
    "length": 67,
    "parts": [
      {
        "id": "arm9.0053.00"
      },
      {
        "text": "%e"
      }
    ]
  },
  {
    "id": "arm9.0054",
    "pos": 362732,
    "length": 71,
    "parts": [
      {
        "id": "arm9.0054.00"
      },
      {
        "text": "%e"
      }
    ]
  },
  {
    "id": "arm9.0055",
    "pos": 362804,
    "length": 71,
    "parts": [
      {
        "id": "arm9.0055.00"
      },
      {
        "text": "%e"
      }
    ]
  },
  {
    "id": "arm9.0056",
    "pos": 362876,
    "length": 71,
    "parts": [
      {
        "id": "arm9.0056.00"
      },
      {
        "text": "%e"
      }
    ]
  },
  {
    "id": "arm9.0057",
    "pos": 362948,
    "length": 71,
    "parts": [
      {
        "id": "arm9.0057.00"
      },
      {
        "text": "%e"
      }
    ]
  },
  {
    "id": "arm9.0058",
    "pos": 363020,
    "length": 71,
    "parts": [
      {
        "id": "arm9.0058.00"
      },
      {
        "text": "%e"
      }
    ]
  },
  {
    "id": "arm9.0059",
    "pos": 363092,
    "length": 75,
    "parts": [
      {
        "id": "arm9.0059.00"
      },
      {
        "text": "%e"
      }
    ]
  },
  {
    "id": "arm9.0060",
    "pos": 363168,
    "length": 75,
    "parts": [
      {
        "id": "arm9.0060.00"
      },
      {
        "text": "%e"
      }
    ]
  },
  {
    "id": "arm9.0061",
    "pos": 363244,
    "length": 79,
    "parts": [
      {
        "id": "arm9.0061.00"
      },
      {
        "text": "%e"
      }
    ]
  },
  {
    "id": "arm9.0062",
    "pos": 363404,
    "length": 83,
    "parts": [
      {
        "id": "arm9.0062.00"
      },
      {
        "text": "%e"
      }
    ]
  },
  {
    "id": "arm9.0063",
    "pos": 363488,
    "length": 83,
    "parts": [
      {
        "id": "arm9.0063.00"
      },
      {
        "text": "%e"
      }
    ]
  },
  {
    "id": "arm9.0064",
    "pos": 363572,
    "length": 83,
    "parts": [
      {
        "id": "arm9.0064.00"
      },
      {
        "text": "%e"
      }
    ]
  },
  {
    "id": "arm9.0065",
    "pos": 363740,
    "length": 83,
    "parts": [
      {
        "id": "arm9.0065.00"
      },
      {
        "text": "%e"
      }
    ]
  },
  {
    "id": "arm9.0066",
    "pos": 363824,
    "length": 87,
    "parts": [
      {
        "id": "arm9.0066.00"
      },
      {
        "text": "%e"
      }
    ]
  },
  {
    "id": "arm9.0067",
    "pos": 363912,
    "length": 87,
    "parts": [
      {
        "id": "arm9.0067.00"
      },
      {
        "text": "%e"
      }
    ]
  },
  {
    "id": "arm9.0068",
    "pos": 364000,
    "length": 91,
    "parts": [
      {
        "id": "arm9.0068.00"
      },
      {
        "text": "%e"
      }
    ]
  },
  {
    "id": "arm9.0069",
    "pos": 364092,
    "length": 91,
    "parts": [
      {
        "id": "arm9.0069.00"
      },
      {
        "text": "%e"
      }
    ]
  },
  {
    "id": "arm9.0070",
    "pos": 364184,
    "length": 91,
    "parts": [
      {
        "id": "arm9.0070.00"
      },
      {
        "text": "%e"
      }
    ]
  },
  {
    "id": "arm9.0071",
    "pos": 364276,
    "length": 95,
    "parts": [
      {
        "id": "arm9.0071.00"
      },
      {
        "text": "%e"
      }
    ]
  },
  {
    "id": "arm9.0072",
    "pos": 364372,
    "length": 99,
    "parts": [
      {
        "id": "arm9.0072.00"
      },
      {
        "text": "%e"
      }
    ]
  },
  {
    "id": "arm9.0073",
    "pos": 364472,
    "length": 103,
    "parts": [
      {
        "id": "arm9.0073.00"
      },
      {
        "text": "%e"
      }
    ]
  },
  {
    "id": "arm9.0074",
    "pos": 364576,
    "length": 103,
    "parts": [
      {
        "id": "arm9.0074.00"
      },
      {
        "text": "%e"
      }
    ]
  },
  {
    "id": "arm9.0075",
    "pos": 364832,
    "length": 159,
    "parts": [
      {
        "id": "arm9.0075.00"
      },
      {
        "text": "%e"
      }
    ]
  },
  {
    "id": "arm9.0076",
    "pos": 364992,
    "length": 159,
    "parts": [
      {
        "id": "arm9.0076.00"
      },
      {
        "text": "%e"
      }
    ]
  },
  {
    "id": "arm9.0077",
    "pos": 365152,
    "length": 163,
    "parts": [
      {
        "id": "arm9.0077.00"
      },
      {
        "text": "%e"
      }
    ]
  },
  {
    "id": "arm9.0078",
    "pos": 365316,
    "length": 175,
    "parts": [
      {
        "id": "arm9.0078.00"
      },
      {
        "text": "%e"
      }
    ]
  },
  {
    "id": "arm9.0079",
    "pos": 365492,
    "length": 207,
    "parts": [
      {
        "id": "arm9.0079.00"
      },
      {
        "text": "%e"
      }
    ]
  },
  {
    "id": "arm9.0080",
    "pos": 365700,
    "length": 275,
    "parts": [
      {
        "id": "arm9.0080.00"
      },
      {
        "text": "%e"
      }
    ]
  },
  {
    "id": "arm9.0081",
    "pos": 365976,
    "length": 315,
    "parts": [
      {
        "id": "arm9.0081.00"
      },
      {
        "text": "%e"
      }
    ]
  },
  {
    "id": "arm9.0082",
    "pos": 366292,
    "length": 347,
    "parts": [
      {
        "id": "arm9.0082.00"
      },
      {
        "text": "%e"
      }
    ]
  },
  {
    "id": "arm9.0083",
    "pos": 366640,
    "length": 367,
    "parts": [
      {
        "id": "arm9.0083.00"
      },
      {
        "text": "%e"
      }
    ]
  },
  {
    "id": "arm9.0084",
    "pos": 367008,
    "length": 407,
    "parts": [
      {
        "id": "arm9.0084.00"
      },
      {
        "text": "%e"
      }
    ]
  },
  {
    "id": "arm9.0085",
    "pos": 367416,
    "length": 411,
    "parts": [
      {
        "id": "arm9.0085.00"
      },
      {
        "text": "%e"
      }
    ]
  },
  {
    "id": "arm9.0086",
    "pos": 367828,
    "length": 459,
    "parts": [
      {
        "id": "arm9.0086.00"
      },
      {
        "text": "%e"
      }
    ]
  },
  {
    "id": "arm9.0087",
    "pos": 368288,
    "length": 459,
    "parts": [
      {
        "id": "arm9.0087.00"
      },
      {
        "text": "%e"
      }
    ]
  },
  {
    "id": "arm9.0088",
    "pos": 368748,
    "length": 495,
    "parts": [
      {
        "id": "arm9.0088.00"
      },
      {
        "text": "%e"
      }
    ]
  },
  {
    "id": "arm9.0089",
    "pos": 369244,
    "length": 547,
    "parts": [
      {
        "id": "arm9.0089.00"
      },
      {
        "text": "%e"
      }
    ]
  },
  {
    "id": "arm9.0090",
    "pos": 369792,
    "length": 567,
    "parts": [
      {
        "id": "arm9.0090.00"
      },
      {
        "text": "%e"
      }
    ]
  },
  {
    "id": "arm9.0091",
    "pos": 370360,
    "length": 587,
    "parts": [
      {
        "id": "arm9.0091.00"
      },
      {
        "text": "%e"
      }
    ]
  },
  {
    "id": "arm9.0092",
    "pos": 370948,
    "length": 591,
    "parts": [
      {
        "id": "arm9.0092.00"
      },
      {
        "text": "%e"
      }
    ]
  },
  {
    "id": "arm9.0093",
    "pos": 371540,
    "length": 595,
    "parts": [
      {
        "id": "arm9.0093.00"
      },
      {
        "text": "%e"
      }
    ]
  },
  {
    "id": "arm9.0094",
    "pos": 372136,
    "length": 643,
    "parts": [
      {
        "id": "arm9.0094.00"
      },
      {
        "text": "%e"
      }
    ]
  },
  {
    "id": "arm9.0095",
    "pos": 372780,
    "length": 659,
    "parts": [
      {
        "id": "arm9.0095.00"
      },
      {
        "text": "%e"
      }
    ]
  },
  {
    "id": "arm9.0096",
    "pos": 373480,
    "length": 15
  },
  {
    "id": "arm9.0097",
    "pos": 373524,
    "length": 23
  },
  {
    "id": "arm9.0098",
    "pos": 373564,
    "length": 11
  },
  {
    "id": "arm9.0099",
    "pos": 373576,
    "length": 11
  },
  {
    "id": "arm9.0100",
    "pos": 373588,
    "length": 11
  },
  {
    "id": "arm9.0101",
    "pos": 373600,
    "length": 19
  },
  {
    "id": "arm9.0102",
    "pos": 373620,
    "length": 19
  },
  {
    "id": "arm9.0103",
    "pos": 373640,
    "length": 15
  },
  {
    "id": "arm9.0104",
    "pos": 373656,
    "length": 15
  },
  {
    "id": "arm9.0105",
    "pos": 373672,
    "length": 19
  },
  {
    "id": "arm9.0106",
    "pos": 373692,
    "length": 11
  },
  {
    "id": "arm9.0107",
    "pos": 373704,
    "length": 7
  },
  {
    "id": "arm9.0108",
    "pos": 373712,
    "length": 7
  },
  {
    "id": "arm9.0109",
    "pos": 373720,
    "length": 19
  },
  {
    "id": "arm9.0110",
    "pos": 373740,
    "length": 19
  },
  {
    "id": "arm9.0111",
    "pos": 373760,
    "length": 23
  },
  {
    "id": "arm9.0112",
    "pos": 373784,
    "length": 19
  },
  {
    "id": "arm9.0113",
    "pos": 373804,
    "length": 19
  },
  {
    "id": "arm9.0114",
    "pos": 373824,
    "length": 23
  },
  {
    "id": "arm9.0115",
    "pos": 373848,
    "length": 15
  },
  {
    "id": "arm9.0116",
    "pos": 373864,
    "length": 19
  },
  {
    "id": "arm9.0117",
    "pos": 373884,
    "length": 19
  },
  {
    "id": "arm9.0118",
    "pos": 373904,
    "length": 15
  },
  {
    "id": "arm9.0119",
    "pos": 373920,
    "length": 19
  },
  {
    "id": "arm9.0120",
    "pos": 373940,
    "length": 19
  },
  {
    "id": "arm9.0121",
    "pos": 373960,
    "length": 19
  },
  {
    "id": "arm9.0122",
    "pos": 373980,
    "length": 19
  },
  {
    "id": "arm9.0123",
    "pos": 374000,
    "length": 23
  },
  {
    "id": "arm9.0124",
    "pos": 374024,
    "length": 15
  },
  {
    "id": "arm9.0125",
    "pos": 374040,
    "length": 23
  },
  {
    "id": "arm9.0126",
    "pos": 374064,
    "length": 15
  },
  {
    "id": "arm9.0127",
    "pos": 374080,
    "length": 23
  },
  {
    "id": "arm9.0128",
    "pos": 374104,
    "length": 15
  },
  {
    "id": "arm9.0129",
    "pos": 374120,
    "length": 19
  },
  {
    "id": "arm9.0130",
    "pos": 374140,
    "length": 19
  },
  {
    "id": "arm9.0131",
    "pos": 374160,
    "length": 19
  },
  {
    "id": "arm9.0132",
    "pos": 374180,
    "length": 23
  },
  {
    "id": "arm9.0133",
    "pos": 374204,
    "length": 15
  },
  {
    "id": "arm9.0134",
    "pos": 374220,
    "length": 23
  },
  {
    "id": "arm9.0135",
    "pos": 374244,
    "length": 23
  },
  {
    "id": "arm9.0136",
    "pos": 374268,
    "length": 23
  },
  {
    "id": "arm9.0137",
    "pos": 374292,
    "length": 19
  },
  {
    "id": "arm9.0138",
    "pos": 374312,
    "length": 15
  },
  {
    "id": "arm9.0139",
    "pos": 374328,
    "length": 19
  },
  {
    "id": "arm9.0140",
    "pos": 374348,
    "length": 15
  },
  {
    "id": "arm9.0141",
    "pos": 374364,
    "length": 23
  },
  {
    "id": "arm9.0142",
    "pos": 374388,
    "length": 31
  },
  {
    "id": "arm9.0143",
    "pos": 374424,
    "length": 31
  },
  {
    "id": "arm9.0144",
    "pos": 374456,
    "length": 15
  },
  {
    "id": "arm9.0145",
    "pos": 376100,
    "length": 55,
    "parts": [
      {
        "id": "arm9.0145.00"
      },
      {
        "text": "%e"
      }
    ]
  },
  {
    "id": "arm9.0146",
    "pos": 376156,
    "length": 55,
    "parts": [
      {
        "id": "arm9.0146.00"
      },
      {
        "text": "%e"
      }
    ]
  },
  {
    "id": "arm9.0147",
    "pos": 376272,
    "length": 83,
    "parts": [
      {
        "id": "arm9.0147.00"
      },
      {
        "text": "%e"
      }
    ]
  },
  {
    "id": "arm9.0148",
    "pos": 376356,
    "length": 95,
    "parts": [
      {
        "id": "arm9.0148.00"
      },
      {
        "text": "%e"
      }
    ]
  },
  {
    "id": "arm9.0149",
    "pos": 376452,
    "length": 123,
    "parts": [
      {
        "id": "arm9.0149.00"
      },
      {
        "text": "%e"
      }
    ]
  },
  {
    "id": "arm9.0150",
    "pos": 376584,
    "length": 15
  },
  {
    "id": "arm9.0151",
    "pos": 376600,
    "length": 15
  }
]