{
    "overlay_0006.0002": "門",
    "overlay_0006.0004": "柱",
    "overlay_0006.0005": "岩石",
    "overlay_0006.0006": "岩肌",
    "overlay_0006.0008": "門の奥",
    "overlay_0006.0009": "墓地への道",
    "overlay_0006.0010.00": "%w(200)%f(2)茂み%f(0)には何もない%h",
    "overlay_0006.0011.00": "%w(200)%f(2)ゲートの跡%f(0)がある%h",
    "overlay_0006.0012.00": "%w(200)%f(0)きれいな%f(2)空%f(0)だ%h",
    "overlay_0006.0013.00": "%w(200)%f(2)道%f(0)は閉ざされている%h",
    "overlay_0006.0014.00": "%w(200)%f(0)大きな%f(2)木%f(0)がある%h",
    "overlay_0006.0015.00": "%w(200)%f(0)岩肌の%f(2)壁%f(0)がある%h",
    "overlay_0006.0016.00": "%w(200)%f(0)レンガの%f(2)門%f(0)がある%h",
    "overlay_0006.0017.00": "%w(200)%f(2)木々%f(0)は青々と茂っている%h",
    "overlay_0006.0018.00": "%w(200)%f(2)門の奥%f(0)には建物が見える%h",
    "overlay_0006.0019.00": "%w(200)%f(2)茂み%f(0)には何も落ちていない%h",
    "overlay_0006.0020.00": "%w(200)%f(2)道%f(0)の先は、少し暗くなっている%h",
    "overlay_0006.0021.00": "%w(200)%f(0)たくさんの%f(2)木%f(0)が生えている%h",
    "overlay_0006.0022.00": "%w(200)%f(0)木々の隙間から%f(2)空%f(0)が覗いている%h",
    "overlay_0006.0023.00": "%w(200)%f(0)大きな%f(2)落石%f(0)で、道は閉ざされている%h",
    "overlay_0006.0024.00": "%w(200)%f(0)レンガの%f(2)門%f(0)の向こうには%h\n%w(200)坑道口の跡がある%h",
    "overlay_0006.0025.00": "%w(200)%f(0)レンガの%f(2)門%f(0)が見える%h\n%w(110)%C(0_016)あの先には何があるの？%h",
    "overlay_0006.0026.00": "%w(110)%C(0_006)%z(04)%z(130)%f(0)あっ…！%h\n%w(110)%C(0_006)…大きな岩で%t(20)%r\n道が…ふさがれている！%h\n%w(110)%C(0_015)%z(02)…どうしよう%h"
}
